[{"model": "savedata.creditloanproducts", "pk": 1, "fields": {"fin_prdt_cd": "CR0001A", "kor_co_nm": "우리은행", "fin_co_no": "0010001", "fin_prdt_nm": "개인신용대출 우대고객", "join_way": "영업점,인터넷,스마트폰", "crdt_prdt_type": 1, "crdt_prdt_type_nm": "일반신용대출", "cb_name": "KCB", "dcls_strt_day": "2024-05-17", "dcls_end_day": "9999-12-31"}}, {"model": "savedata.creditloanproducts", "pk": 2, "fields": {"fin_prdt_cd": "CR0001C", "kor_co_nm": "우리은행", "fin_co_no": "0010001", "fin_prdt_nm": "개인신용대출 퍼펙트", "join_way": "영업점,인터넷,스마트폰", "crdt_prdt_type": 1, "crdt_prdt_type_nm": "일반신용대출", "cb_name": "KCB", "dcls_strt_day": "2024-05-17", "dcls_end_day": "9999-12-31"}}, {"model": "savedata.creditloanproducts", "pk": 3, "fields": {"fin_prdt_cd": "WR0001F", "kor_co_nm": "대구은행", "fin_co_no": "0010016", "fin_prdt_nm": "일반신용대출", "join_way": "영업점,스마트폰", "crdt_prdt_type": 1, "crdt_prdt_type_nm": "일반신용대출", "cb_name": "KCB", "dcls_strt_day": "2024-05-20", "dcls_end_day": "2024-06-30"}}, {"model": "savedata.creditloanproducts", "pk": 4, "fields": {"fin_prdt_cd": "WR0002F", "kor_co_nm": "대구은행", "fin_co_no": "0010016", "fin_prdt_nm": "마이너스한도대출", "join_way": "영업점,스마트폰", "crdt_prdt_type": 2, "crdt_prdt_type_nm": "마이너스한도대출", "cb_name": "KCB", "dcls_strt_day": "2024-05-20", "dcls_end_day": "2024-06-30"}}, {"model": "savedata.creditloanproducts", "pk": 5, "fields": {"fin_prdt_cd": "CR0001A", "kor_co_nm": "전북은행", "fin_co_no": "0010022", "fin_prdt_nm": "가계일반자금대출", "join_way": "영업점,모집인", "crdt_prdt_type": 1, "crdt_prdt_type_nm": "일반신용대출", "cb_name": "KCB", "dcls_strt_day": "2024-05-20", "dcls_end_day": "2024-06-19"}}, {"model": "savedata.creditloanproducts", "pk": 6, "fields": {"fin_prdt_cd": "CR0001C", "kor_co_nm": "전북은행", "fin_co_no": "0010022", "fin_prdt_nm": "평생종합통장", "join_way": "영업점,모집인", "crdt_prdt_type": 2, "crdt_prdt_type_nm": "마이너스한도대출", "cb_name": "KCB", "dcls_strt_day": "2024-05-20", "dcls_end_day": "2024-06-19"}}, {"model": "savedata.creditloanproducts", "pk": 7, "fields": {"fin_prdt_cd": "21", "kor_co_nm": "중소기업은행", "fin_co_no": "0010026", "fin_prdt_nm": "일반신용대출", "join_way": "영업점,스마트폰,모집인", "crdt_prdt_type": 1, "crdt_prdt_type_nm": "일반신용대출", "cb_name": "NICE", "dcls_strt_day": "2024-05-17", "dcls_end_day": "2025-05-17"}}, {"model": "savedata.creditloanproducts", "pk": 8, "fields": {"fin_prdt_cd": "31", "kor_co_nm": "중소기업은행", "fin_co_no": "0010026", "fin_prdt_nm": "마이너스한도대출", "join_way": "영업점,스마트폰,모집인", "crdt_prdt_type": 2, "crdt_prdt_type_nm": "마이너스한도대출", "cb_name": "NICE", "dcls_strt_day": "2024-05-17", "dcls_end_day": "2025-05-17"}}]